auto_propensity/__init__.py
auto_propensity/builder.py
auto_propensity/core.py
auto_propensity/handler.py
auto_propensity/model.py
auto_propensity-0.1.0.dist-info/METADATA
auto_propensity-0.1.0.dist-info/WHEEL
auto_propensity-0.1.0.dist-info/top_level.txt
auto_propensity-0.1.0.dist-info/RECORD
