Metadata-Version: 2.4
Name: auto-propensity
Version: 0.1.0
Summary: Automated propensity model selection and scoring for discrete/continuous actions.
Author: Saeid Tayebi
License-Expression: Apache-2.0
Project-URL: Homepage, https://github.com/Saeid-Tayebi/AutoPropensity
Requires-Python: >=3.10
Requires-Dist: numpy
Requires-Dist: scikit-learn
Requires-Dist: scipy
Requires-Dist: matplotlib
